cipher_asa2249/__init__.py
cipher_asa2249/cipher_asa2249.py
cipher_asa2249-0.1.0.dist-info/LICENSE
cipher_asa2249-0.1.0.dist-info/WHEEL
cipher_asa2249-0.1.0.dist-info/METADATA
cipher_asa2249-0.1.0.dist-info/RECORD
