Metadata-Version: 2.1
Name: cipher-asa2249
Version: 0.1.0
Summary: A package for eencrypting and decrypting text using the cipher algorithm.
License: MIT
Author: Armaan Ahmed
Requires-Python: >=3.9,<4.0
Classifier: License :: OSI Approved :: MIT License
Classifier: Programming Language :: Python :: 3
Classifier: Programming Language :: Python :: 3.9
Requires-Dist: pytest (>=6.2.5,<7.0.0)
